m3u8_analyzer/M3u8Analyzer.py
m3u8_analyzer/__config__.py
m3u8_analyzer/__init__.py
m3u8_analyzer/__version__.py
m3u8_analyzer/exeptions.py
m3u8_analyzer-1.0.4.4.dist-info/METADATA
m3u8_analyzer-1.0.4.4.dist-info/WHEEL
m3u8_analyzer-1.0.4.4.dist-info/top_level.txt
m3u8_analyzer-1.0.4.4.dist-info/RECORD
