Metadata-Version: 2.1
Name: m3u8-analyzer
Version: 1.0.4.4
Summary: Análise de dados de HLS m3u8
Home-page: https://paulocesar-dev404.github.io/M3u8_Analyzer/
Author: PauloCesar0073-dev404
Author-email: paulocesar0073dev404@gmail.com
License: MIT
Keywords: hls,m3u8,m3u8_analyzer,M3u8Analyzer
Platform: any
Classifier: Development Status :: 5 - Production/Stable
Classifier: Intended Audience :: Developers
Classifier: License :: OSI Approved :: MIT License
Classifier: Programming Language :: Python :: 3.10
Classifier: Programming Language :: Python :: 3.11
Classifier: Programming Language :: Python :: 3.12
Classifier: Operating System :: OS Independent
Requires-Dist: colorama
Requires-Dist: requests
Requires-Dist: cryptography
